{
  "date": "2026-06-26",
  "title": "[6.25] 미국 트럼프, 이란 크게 양보했다며 압박. Micron Technology 실적은 예상 상회 등",
  "source_url": "https://www.kcif.or.kr/annual/reportView?rpt_no=37234&mn=001002",
  "market_data": {
    "sp500": {
      "value": "7,357.5",
      "change": "-0.01%"
    },
    "kospi": {
      "value": "8,471.02",
      "change": "+3.26%"
    },
    "usd_krw": {
      "value": "1,544.2",
      "change": "+0.09%"
    },
    "wti": {
      "value": "71.45",
      "change": "+1.58%"
    },
    "gold": {
      "value": "4,037.7",
      "change": "+1.19%"
    },
    "vix": {
      "value": "18.89",
      "change": "+1.40%"
    },
    "dxy": {
      "value": "101.44",
      "change": "-0.17%"
    },
    "us10y": {
      "value": "4.392",
      "change": "-1.33%"
    },
    "eurusd": {
      "value": "1.1373",
      "change": "+0.16%"
    },
    "usdjpy": {
      "value": "161.76",
      "change": "+0.00%"
    }
  },
  "bull": "# 📈 오늘의 시장 분석 (6.25)\n\n---\n\n## 1️⃣ 오늘의 핵심 판단\n\n**\"KOSPI의 강력한 상승이 증명하는 아시아 투자 기회, 지금이 진입 타이밍\"**\n\nKOSPI +3.26%의 강한 상승은 단순한 기술적 반등이 아닌 글로벌 자금의 아시아 재배분 신호로 읽힙니다. Micron의 어닝 서프라이즈가 반도체 섹터 전반의 실적 모멘텀을 확인시켜 주면서, 한국 주식시장의 밸류에이션 매력이 다시 한번 부각되는 국면입니다. 미·이란 협상 진전까지 더해지며 지정학적 리스크 완화 기대감이 상승 동력을 뒷받침하고 있습니다.\n\n---\n\n## 2️⃣ 시장 분석\n\n**🇺🇸 미국:** S&P 500은 사실상 보합(-0.01%)으로 고점권에서 견조하게 버티는 모습이며, 미 10년물 금리가 -1.33% 하락하며 채권시장이 성장 친화적 신호를 보내고 있습니다. 연준의 대형은행 스트레스 테스트 통과는 금융시스템의 안정성을 재확인해 주는 강력한 안전판입니다.\n\n**🇰🇷 한국/아시아:** KOSPI의 +3.26% 급등은 외국인 수급 개선과 반도체 업황 회복 기대가 맞물린 결과로, 삼성전자·SK하이닉스 중심의 밸류업 랠리가 본격화될 가능성이 높습니다. 원/달러 환율이 1,544원 수준에서 안정적으로 유지되는 점도 외국인 투자자 입장에서 추가 매수 유인이 됩니다.\n\n**🛢️ 원자재:** WTI +1.58%, 금 +1.19%의 동반 상승은 인플레이션 헤지 수요와 경기 회복 기대감이 동시",
  "bear": "# 🐻 약세론자의 시장 분석 — 2025.06.25\n\n---\n\n## 1️⃣ 오늘의 핵심 판단\n\n**\"KOSPI 급등의 이면에 숨겨진 경고등들\"**\n\nKOSPI 3.26% 급등은 표면적으로 긍정적이나, 이와 동시에 VIX 상승(+1.40%)과 금 가격 강세(+1.19%)가 병행되는 것은 **시장 내부의 불안 심리가 엄연히 살아있음**을 시사합니다. 위험자산과 안전자산이 동반 상승하는 구도는 방향성보다 **불확실성의 증폭**을 의미하며, 이런 국면에서의 낙관론은 위험합니다.\n\n---\n\n## 2️⃣ 시장 분석\n\n### 📌 KOSPI 급등 — 진짜 체력인가, 수급 착시인가\nKOSPI 8,471 돌파는 인상적이지만, 원/달러 환율이 여전히 1,544원대 고공행진 중이라는 점에서 **외국인 실질 수익률은 크게 훼손**된 상태입니다. 강달러-원화약세 구조가 고착될 경우 외국인 자금의 이탈 압력이 재점화될 수 있으며, 지수 상승의 지속성에 의문을 제기할 수밖에 없습니다.\n\n### 📌 미·이란 협상 — 불확실성 프리미엄은 걷히지 않았다\n트럼프의 \"이란이 크게 양보했다\"는 발언은 유가를 자극하고 있으나, **주요 사안이 미해결 상태**라는 점에서 언제든 협상 결렬 시나리오로 반전될 수 있습니다. WTI +1.58% 반등은 지정학적 리스크 프리미엄의 재확인이며, 유가 변동성은 인플레이션 경로의 최대 불확실 변수로 남습니다.\n\n### 📌 미 국채금리 하락 + 달러 약세 — 연준 기대 선반영의 함정\n10년",
  "quant": "# 📊 퀀트 데이터 브리핑 | 6.25\n\n---\n\n## 1️⃣ 오늘의 핵심 판단\n\nS&P 500이 -0.01%로 사실상 보합에 머문 반면, KOSPI는 +3.26%의 강한 아웃퍼폼을 기록했습니다. VIX 18.89(+1.40%)는 공포 임계치(20)를 하회하며 미국 시장의 변동성 확대 우려가 현실화되진 않았으나, 상승 방향성을 유지하고 있습니다. 금(+1.19%)과 국채 동반 강세(10Y -1.33bp), WTI(+1.58%) 동시 상승은 **지정학적 불확실성이 혼재된 복합 국면**임을 시사합니다.\n\n---\n\n## 2️⃣ 시장 분석\n\n**[변동성·위험선호]** VIX 18.89는 중립~경계 구간에 위치하며, AI 버블 붕괴 담론이 유통되는 가운데도 S&P 500이 7,357선을 유지 — 대형 매도 압력은 아직 비가시화 상태입니다. Micron 실적 서프라이즈(예상 상회)는 반도체·AI 섹터의 실적 펀더멘털이 내러티브를 지지하고 있음을 데이터로 확인해줍니다.\n\n**[환율·금리]** 달러인덱스 101.44(-0.17%)와 USD/JPY 161.76(보합)의 디커플링은 주목할 포인트입니다. 엔화 약세가 지속되는 구조에서 BOJ 총재의 금리인상 지속 발언은 **엔 캐리 청산 리스크의 잠재적 트리거**로 계량적 모니터링이 필요합니다. 원/달러 1,544.2는 KOSPI 강세에도 불구하고 소폭 상승(+0.09%), 외국인 순매수의 헤지 수요 또는 달러 수급 요인이 상쇄 중입니다.\n\n**[원자재·지정학]** WTI +1.58%는 미-이란",
  "buffett": "# 📊 버핏의 눈으로 본 오늘의 시장 (6.25)\n\n---\n\n## 1️⃣ 오늘의 핵심 판단\n\n**\"KOSPI의 급등은 흥분할 일이 아니라 차분히 들여다볼 신호다.\"**\n\nKOSPI 3.26% 급등은 분명 시선을 끌지만, 버핏이라면 \"왜 오늘 이 가격인가\"를 먼저 물었을 것입니다. 단기 모멘텀이 아닌, 이 가격이 실제 기업 가치를 반영하는지가 핵심 질문입니다. S&P 500이 사실상 보합(-0.01%)인 상황에서 한국 시장의 독립적 상승은 펀더멘털보다 수급·심리 요인일 가능성이 높습니다.\n\n---\n\n## 2️⃣ 시장 분석\n\n**💵 달러·금리:** 미국 10년물 금리가 4.39%로 소폭 하락하고 달러 인덱스도 약해지는 흐름은 **긴축 사이클의 끝자락** 신호로 읽힙니다. 원/달러 1,544원은 여전히 역사적 고점 근방으로, 한국 자산의 달러 환산 가치가 그만큼 저평가 구간에 있다는 뜻이기도 합니다.\n\n**🛢️ 유가·금:** WTI 71달러대와 금 4,037달러의 동반 상승은 시장이 **지정학적 불확실성(이란 협상)**을 아직 완전히 가격에 반영하지 않았음을 보여줍니다. 금이 4,000달러를 넘어선 지금, 금은 \"안전자산\"이 아니라 **불안의 온도계**로 보는 시각이 더 정확합니다.\n\n**🤖 Micron 실적:** AI 인프라 수요가 메모리 반도체 실적을 끌어올리고 있다는 것은, 버블 우려에도 불구하고 **AI 관련 실물 수요는 진짜**임을 확인해주는 대목입니다. 다만 \""
}